PyLLSM5DTools/XR_FSC_analysis_wrapper.py
PyLLSM5DTools/XR_MIP_wrapper.py
PyLLSM5DTools/XR_crop_dataset.py
PyLLSM5DTools/XR_decon_data_wrapper.py
PyLLSM5DTools/XR_deskew_rotate_data_wrapper.py
PyLLSM5DTools/XR_fftSpectrumComputingWrapper.py
PyLLSM5DTools/XR_matlab_stitching_wrapper.py
PyLLSM5DTools/XR_microscopeAutomaticProcessing.py
PyLLSM5DTools/XR_psf_analysis_wrapper.py
PyLLSM5DTools/XR_psf_detection_and_analysis_wrapper.py
PyLLSM5DTools/XR_resample_dataset.py
PyLLSM5DTools/XR_tiffToZarr_wrapper.py
PyLLSM5DTools/XR_visualize_OTF_mask_segmentation.py
PyLLSM5DTools/XR_zarrToTiff_wrapper.py
PyLLSM5DTools/__init__.py
PyLLSM5DTools/generatePythonWrapper.py
PyLLSM5DTools/generate_config_file.py
PyLLSM5DTools-1.1.3.dist-info/LICENSE.txt
PyLLSM5DTools-1.1.3.dist-info/METADATA
PyLLSM5DTools-1.1.3.dist-info/WHEEL
PyLLSM5DTools-1.1.3.dist-info/top_level.txt
PyLLSM5DTools-1.1.3.dist-info/RECORD
