Metadata-Version: 2.1
Name: PyLLSM5DTools
Version: 1.1.3
Summary: A Python wrapper for LLSM5DTools
Home-page: https://github.com/abcucberkeley/PyLLSM5DTools
Author: Matthew Mueller
Author-email: matthewmueller@berkeley.edu
License: GPL-3.0
Classifier: Intended Audience :: Science/Research
Classifier: Operating System :: POSIX :: Linux
Classifier: Programming Language :: Python :: 3.11
License-File: LICENSE.txt
